pybotlearn/__init__.py
pybotlearn/bot.py
pybotlearn/loop.py
pybotlearn-1.0.1.dist-info/METADATA
pybotlearn-1.0.1.dist-info/WHEEL
pybotlearn-1.0.1.dist-info/top_level.txt
pybotlearn-1.0.1.dist-info/RECORD
