Metadata-Version: 2.1
Name: pybotlearn
Version: 1.0.1
Summary: Uma biblioteca Python para criar bots mais ou menos inteligentes.
Home-page: UNKNOWN
Author: jose
Author-email: reginaldasmcosta@gmail.com
License: UNKNOWN
Platform: UNKNOWN
Requires-Python: >=3.6
